[
    {
        "Name": "First",
        "Index" : 0,
        "Active": true,
        "KeyMap": ["A", "w", "e", "r", "t", "N1","N2","N3","N4","N5"],
        "EncoderMap": ["VOLU", "VOLD", "MUTE"]
    },
    {
        "Name":"Second",
        "Index" : 1,
        "Active": true,
        "App" : "notepad++",
        "KeyMap":  ["N1","N2","N3","N4","N5", "Q", "w", "e", "r", "t"],
        "EncoderMap": ["VOLU", "VOLD", "MUTE"]
    },{
        "Name":"Another",
        "Index" : 2,
        "Active": true,
        "App" : "notepad++",
        "KeyMap":  ["X","Y","U","I","YU", "O", "w", "e", "r", "t"],
        "EncoderMap": ["VOLU", "VOLD", "MUTE"]
    },{
        "Name":"Third",
        "Index" : 3,
        "Active": true,
        "App" : "notepad++",
        "KeyMap":  ["A","B","C","D","E", "F", "G", "H", "I", "J"],
        "EncoderMap": ["VOLU", "VOLD", "MUTE"]
    }
]